MANIFEST.in
setup.py
docs/HISTORY.txt
docs/README.txt
docs/TODO.txt
quintagroup/__init__.py
quintagroup.themetemplate.egg-info/PKG-INFO
quintagroup.themetemplate.egg-info/SOURCES.txt
quintagroup.themetemplate.egg-info/dependency_links.txt
quintagroup.themetemplate.egg-info/entry_points.txt
quintagroup.themetemplate.egg-info/namespace_packages.txt
quintagroup.themetemplate.egg-info/not-zip-safe
quintagroup.themetemplate.egg-info/requires.txt
quintagroup.themetemplate.egg-info/top_level.txt
quintagroup/themetemplate/README.txt
quintagroup/themetemplate/__init__.py
quintagroup/themetemplate/qplone3_theme.py
quintagroup/themetemplate/localcommands/__init__.py
quintagroup/themetemplate/localcommands/subtemplates.py
quintagroup/themetemplate/localcommands/templates/cssresource/browser/configure.zcml_insert
quintagroup/themetemplate/localcommands/templates/cssresource/browser/stylesheets/+css_resource_name+_tmpl
quintagroup/themetemplate/localcommands/templates/cssresource/browser/stylesheets/README.txt_tmpl
quintagroup/themetemplate/localcommands/templates/cssresource/profiles/default/cssregistry.xml_insert
quintagroup/themetemplate/localcommands/templates/cssskinresource/profiles/default/cssregistry.xml_insert
quintagroup/themetemplate/localcommands/templates/cssskinresource/skins/+layer_name+/+css_resource_name+.dtml_tmpl
quintagroup/themetemplate/localcommands/templates/importing/fixes.py_tmpl
quintagroup/themetemplate/localcommands/templates/importing/profiles.zcml_insert
quintagroup/themetemplate/localcommands/templates/importing/setuphandlers.py_insert
quintagroup/themetemplate/localcommands/templates/importing/utils.py_tmpl
quintagroup/themetemplate/localcommands/templates/importing/import/CONTENT.txt
quintagroup/themetemplate/localcommands/templates/importing/profiles/import_zexps/import_steps.xml_insert
quintagroup/themetemplate/localcommands/templates/jsresource/browser/configure.zcml_insert
quintagroup/themetemplate/localcommands/templates/jsresource/browser/scripts/+js_resource_name+_tmpl
quintagroup/themetemplate/localcommands/templates/jsresource/browser/scripts/README.txt_tmpl
quintagroup/themetemplate/localcommands/templates/jsresource/profiles/default/jsregistry.xml_insert
quintagroup/themetemplate/localcommands/templates/skinlayer/skins.zcml_insert
quintagroup/themetemplate/localcommands/templates/skinlayer/profiles/default/skins.xml_insert
