Metadata-Version: 1.0
Name: quintagroup.themetemplate
Version: 0.25
Summary: Quintagroup theme template for Plone 3 with nested namespace
Home-page: http://svn.quintagroup.com/products/quintagroup.themetemplate
Author: Andriy Mylenkyy
Author-email: support@quintagroup.com
License: GPL
Keywords: ZopeSkel theme template plone3 Quintagroup
Platform: UNKNOWN
Classifier: Programming Language :: Python
Classifier: Topic :: Software Development :: Libraries :: Python Modules
